keepTrace/__init__.py
keepTrace/utils.py
keepTrace-1.2.0.dist-info/METADATA
keepTrace-1.2.0.dist-info/WHEEL
keepTrace-1.2.0.dist-info/license.txt
keepTrace-1.2.0.dist-info/top_level.txt
keepTrace-1.2.0.dist-info/RECORD
