Metadata-Version: 2.1
Name: keepTrace
Version: 1.2.0
Summary: Pickle traceback support. Featuring debuggable restored tracebacks.
Home-page: https://github.com/internetimagery/keepTrace
Author: Jason Dixon
Author-email: jason.dixon.email@gmail.com
License: UNKNOWN
Platform: UNKNOWN
